.bumpversion.cfg
HACKING.rst
LICENSE
MANIFEST.in
README.rst
pytest.ini
setup.cfg
setup.py
appenlight_client/VERSION
appenlight_client/__init__.py
appenlight_client/cli.py
appenlight_client/client.py
appenlight_client/django_middleware.py
appenlight_client/exceptions.py
appenlight_client/ext_json.py
appenlight_client/logger.py
appenlight_client/tests.py
appenlight_client/utils.py
appenlight_client/wsgi.py
appenlight_client.egg-info/PKG-INFO
appenlight_client.egg-info/SOURCES.txt
appenlight_client.egg-info/dependency_links.txt
appenlight_client.egg-info/entry_points.txt
appenlight_client.egg-info/requires.txt
appenlight_client.egg-info/top_level.txt
appenlight_client.egg-info/zip-safe
appenlight_client/ext/__init__.py
appenlight_client/ext/celery.py
appenlight_client/ext/flask.py
appenlight_client/ext/general.py
appenlight_client/ext/pyramid_tween.py
appenlight_client/ext/logging/__init__.py
appenlight_client/ext/logging/logbook.py
appenlight_client/ext/logging/logger.py
appenlight_client/hooks/__init__.py
appenlight_client/hooks/hook_pylons.py
appenlight_client/templates/__init__.py
appenlight_client/templates/default_template.ini
appenlight_client/timing/__init__.py
appenlight_client/timing/timing_chameleon.py
appenlight_client/timing/timing_dbapi2.py
appenlight_client/timing/timing_django_templates.py
appenlight_client/timing/timing_httplib.py
appenlight_client/timing/timing_jinja2.py
appenlight_client/timing/timing_mako.py
appenlight_client/timing/timing_memcache.py
appenlight_client/timing/timing_pylibmc.py
appenlight_client/timing/timing_pymongo.py
appenlight_client/timing/timing_pysolr.py
appenlight_client/timing/timing_redispy.py
appenlight_client/timing/timing_requests.py
appenlight_client/timing/timing_urllib.py
appenlight_client/timing/timing_urllib2.py
appenlight_client/timing/timing_urllib3.py
appenlight_client/transports/__init__.py
appenlight_client/transports/requests.py
appenlight_client/transports/urllib.py
experiements/__init__.py
experiements/test.py
experiements/test2.py