Metadata-Version: 1.1
Name: appenlight-client
Version: 0.6.25
Summary: Client for AppEnlight reporting - WSGI applications and django monitoring (http://getappenlight.com)
Home-page: UNKNOWN
Author: Marcin Lulek
Author-email: info@webreactor.eu
License: BSD
Keywords: monitoring,wsgi,django,flask,pylons,pyramid,debugging,debug,reporting,errors,errormator,appenlight client,sentry alternative
Platform: UNKNOWN
Classifier: Development Status :: 5 - Production/Stable
Classifier: Environment :: Web Environment
Classifier: Framework :: BFG
Classifier: Framework :: CherryPy
Classifier: Framework :: Django
Classifier: Framework :: Flask
Classifier: Framework :: Pylons
Classifier: Framework :: Pyramid
Classifier: Framework :: TurboGears
Classifier: Framework :: Twisted
Classifier: Framework :: Zope2
Classifier: Framework :: Zope3
Classifier: Intended Audience :: Developers
Classifier: License :: OSI Approved :: BSD License
Classifier: Programming Language :: Python :: 2.6
Classifier: Programming Language :: Python :: 2.7
Classifier: Programming Language :: Python :: 3.2
Classifier: Programming Language :: Python :: 3.3
